{"channel_name": "CCTV6", "epg_data": [{"date": "2023-10-26", "start": "00:03", "end": "00:18", "title": "今日影评2023-298"}, {"date": "2023-10-26", "start": "00:18", "end": "01:46", "title": "江南剿匪记之幽灵电台"}, {"date": "2023-10-26", "start": "01:46", "end": "03:19", "title": "甩尾王"}, {"date": "2023-10-26", "start": "03:19", "end": "04:46", "title": "杂技狂人"}, {"date": "2023-10-26", "start": "04:46", "end": "06:54", "title": "夺冠"}, {"date": "2023-10-26", "start": "06:54", "end": "07:09", "title": "核心价值观主题微电影：老讲解"}, {"date": "2023-10-26", "start": "07:09", "end": "08:49", "title": "风云1927"}, {"date": "2023-10-26", "start": "08:49", "end": "10:36", "title": "别有动机"}, {"date": "2023-10-26", "start": "10:36", "end": "12:12", "title": "宋慈之红油纸伞"}, {"date": "2023-10-26", "start": "12:12", "end": "12:19", "title": "音乐电影欣赏"}, {"date": "2023-10-26", "start": "12:19", "end": "14:08", "title": "奇葩朵朵"}, {"date": "2023-10-26", "start": "14:08", "end": "15:43", "title": "太极拳"}, {"date": "2023-10-26", "start": "15:43", "end": "16:28", "title": "我和我的父辈：少年行"}, {"date": "2023-10-26", "start": "16:28", "end": "18:43", "title": "代号东方"}, {"date": "2023-10-26", "start": "18:43", "end": "20:10", "title": "燕赤霞传之情迷兰若寺"}, {"date": "2023-10-26", "start": "20:10", "end": "20:20", "title": "今日影评2023-299"}, {"date": "2023-10-26", "start": "20:20", "end": "22:00", "title": "燕赤霞猎妖传"}, {"date": "2023-10-26", "start": "22:00", "end": "22:22", "title": "中国电影报道2023-299"}, {"date": "2023-10-26", "start": "22:22", "end": "23:00", "title": "一位著名的病人（上）"}, {"date": "2023-10-26", "start": "23:00", "end": "23:03", "title": "中国体育彩票阳光开奖2023-10-26"}, {"date": "2023-10-26", "start": "23:03", "end": "23:58", "title": "一位著名的病人（下）"}, {"date": "2023-10-26", "start": "23:58", "end": "23:59", "title": "音乐电影欣赏"}]}