{"channel_name": "CCTV12", "epg_data": [{"date": "2023-07-12", "start": "00:11", "end": "01:04", "title": "方圆剧阵2023-192"}, {"date": "2023-07-12", "start": "01:04", "end": "01:34", "title": "法律讲堂-2023-185"}, {"date": "2023-07-12", "start": "01:34", "end": "01:55", "title": "生命线-2023-187"}, {"date": "2023-07-12", "start": "01:55", "end": "06:03", "title": "再见"}, {"date": "2023-07-12", "start": "06:03", "end": "06:34", "title": "夕阳红-2023-192"}, {"date": "2023-07-12", "start": "06:34", "end": "06:56", "title": "道德观察(日播版)-2023-192"}, {"date": "2023-07-12", "start": "06:56", "end": "07:30", "title": "法律讲堂（文史版）-2023-132"}, {"date": "2023-07-12", "start": "07:30", "end": "08:15", "title": "一线-2023-137"}, {"date": "2023-07-12", "start": "08:15", "end": "08:35", "title": "生命线-2023-187"}, {"date": "2023-07-12", "start": "08:35", "end": "09:10", "title": "夕阳红-2023-193"}, {"date": "2023-07-12", "start": "09:10", "end": "10:04", "title": "方圆剧阵2021-54"}, {"date": "2023-07-12", "start": "10:04", "end": "10:58", "title": "方圆剧阵2021-55"}, {"date": "2023-07-12", "start": "10:58", "end": "11:30", "title": "天网-2023-136"}, {"date": "2023-07-12", "start": "11:30", "end": "12:00", "title": "热线12-2023-130"}, {"date": "2023-07-12", "start": "12:00", "end": "12:20", "title": "生命线-2023-188"}, {"date": "2023-07-12", "start": "12:20", "end": "12:43", "title": "道德观察(日播版)-2023-192"}, {"date": "2023-07-12", "start": "12:43", "end": "13:28", "title": "2023社会与法电视剧精选-幸福院-10/42"}, {"date": "2023-07-12", "start": "13:28", "end": "14:13", "title": "2023社会与法电视剧精选-幸福院-11/42"}, {"date": "2023-07-12", "start": "14:13", "end": "15:00", "title": "2023社会与法电视剧精选-幸福院-12/42"}, {"date": "2023-07-12", "start": "15:00", "end": "15:30", "title": "天网-2023-136"}, {"date": "2023-07-12", "start": "15:30", "end": "16:02", "title": "热线12-2023-130"}, {"date": "2023-07-12", "start": "16:02", "end": "16:35", "title": "法律讲堂-2023-185"}, {"date": "2023-07-12", "start": "16:35", "end": "17:09", "title": "夕阳红-2023-193"}, {"date": "2023-07-12", "start": "17:09", "end": "17:49", "title": "一线-2023-137"}, {"date": "2023-07-12", "start": "17:49", "end": "18:20", "title": "天网-2023-136"}, {"date": "2023-07-12", "start": "18:20", "end": "18:50", "title": "热线12-2023-131"}, {"date": "2023-07-12", "start": "18:50", "end": "19:22", "title": "法律讲堂-2023-186"}, {"date": "2023-07-12", "start": "19:22", "end": "20:05", "title": "一线-2023-138"}, {"date": "2023-07-12", "start": "20:05", "end": "20:37", "title": "天网-2023-137"}, {"date": "2023-07-12", "start": "20:37", "end": "20:57", "title": "道德观察(日播版)-2023-193"}, {"date": "2023-07-12", "start": "20:57", "end": "21:50", "title": "方圆剧阵2023-193"}, {"date": "2023-07-12", "start": "21:50", "end": "22:25", "title": "法律讲堂（文史版）-2023-133"}, {"date": "2023-07-12", "start": "22:25", "end": "22:55", "title": "热线12-2023-131"}, {"date": "2023-07-12", "start": "22:55", "end": "23:28", "title": "天网-2023-137"}, {"date": "2023-07-12", "start": "23:28", "end": "23:59", "title": "一线-2023-138"}]}