{"channel_name": "云南卫视", "epg_data": [{"date": "2023-07-12", "start": "00:11", "end": "00:53", "title": "劫中劫(15)"}, {"date": "2023-07-12", "start": "00:53", "end": "01:35", "title": "劫中劫(16)"}, {"date": "2023-07-12", "start": "01:35", "end": "02:16", "title": "劫中劫(17)"}, {"date": "2023-07-12", "start": "02:16", "end": "02:56", "title": "劫中劫(18)"}, {"date": "2023-07-12", "start": "02:56", "end": "03:31", "title": "经典人文地理:百年巨匠-李可染"}, {"date": "2023-07-12", "start": "03:31", "end": "04:46", "title": "记住乡愁2"}, {"date": "2023-07-12", "start": "04:46", "end": "05:36", "title": "劫中劫(19)"}, {"date": "2023-07-12", "start": "05:36", "end": "06:24", "title": "劫中劫(20)"}, {"date": "2023-07-12", "start": "06:24", "end": "07:00", "title": "记住乡愁2"}, {"date": "2023-07-12", "start": "07:00", "end": "07:01", "title": "中华人民共和国国歌"}, {"date": "2023-07-12", "start": "07:01", "end": "07:28", "title": "云南新闻联播"}, {"date": "2023-07-12", "start": "07:28", "end": "08:00", "title": "南腔北调(89)"}, {"date": "2023-07-12", "start": "08:00", "end": "08:34", "title": "星光家族(1)"}, {"date": "2023-07-12", "start": "08:34", "end": "09:08", "title": "勇敢的心(31)"}, {"date": "2023-07-12", "start": "09:08", "end": "09:44", "title": "勇敢的心(32)"}, {"date": "2023-07-12", "start": "09:44", "end": "10:48", "title": "勇敢的心(33)"}, {"date": "2023-07-12", "start": "10:48", "end": "11:52", "title": "勇敢的心(34)"}, {"date": "2023-07-12", "start": "11:52", "end": "12:55", "title": "勇敢的心(35)"}, {"date": "2023-07-12", "start": "12:55", "end": "14:00", "title": "薛仁贵传奇(31)"}, {"date": "2023-07-12", "start": "14:00", "end": "15:05", "title": "薛仁贵传奇(32)"}, {"date": "2023-07-12", "start": "15:05", "end": "16:10", "title": "薛仁贵传奇(33)"}, {"date": "2023-07-12", "start": "16:10", "end": "17:14", "title": "薛仁贵传奇(34)"}, {"date": "2023-07-12", "start": "17:14", "end": "18:30", "title": "薛仁贵传奇(35)"}, {"date": "2023-07-12", "start": "18:30", "end": "18:56", "title": "云南新闻联播"}, {"date": "2023-07-12", "start": "18:56", "end": "19:00", "title": "云南天气预报"}, {"date": "2023-07-12", "start": "19:00", "end": "19:38", "title": "转播中央台新闻联播"}, {"date": "2023-07-12", "start": "19:38", "end": "20:27", "title": "国士无双黄飞鸿(28)"}, {"date": "2023-07-12", "start": "20:27", "end": "21:11", "title": "国士无双黄飞鸿(29)"}, {"date": "2023-07-12", "start": "21:11", "end": "21:19", "title": "好剧大放送"}, {"date": "2023-07-12", "start": "21:19", "end": "22:20", "title": "中国智慧中国行(5)"}, {"date": "2023-07-12", "start": "22:20", "end": "22:52", "title": "晚间新闻"}, {"date": "2023-07-12", "start": "22:52", "end": "23:24", "title": "晚间创收性栏目"}, {"date": "2023-07-12", "start": "23:24", "end": "23:59", "title": "经典人文地理:百年巨匠-李可染"}]}