{"channel_name": "北京卫视", "epg_data": [{"date": "2023-10-26", "start": "00:09", "end": "00:52", "title": "父母爱情(4)"}, {"date": "2023-10-26", "start": "00:52", "end": "01:35", "title": "父母爱情(5)"}, {"date": "2023-10-26", "start": "01:35", "end": "01:39", "title": "晚间气象服务"}, {"date": "2023-10-26", "start": "01:39", "end": "02:17", "title": "我的桃花源2(4)"}, {"date": "2023-10-26", "start": "02:17", "end": "03:00", "title": "沸腾人生(34)"}, {"date": "2023-10-26", "start": "03:00", "end": "03:43", "title": "沸腾人生(35)"}, {"date": "2023-10-26", "start": "03:43", "end": "04:25", "title": "沸腾人生(36)"}, {"date": "2023-10-26", "start": "04:25", "end": "05:09", "title": "沸腾人生(37)"}, {"date": "2023-10-26", "start": "05:09", "end": "05:12", "title": "大美北京"}, {"date": "2023-10-26", "start": "05:12", "end": "05:42", "title": "养生堂精编版"}, {"date": "2023-10-26", "start": "05:42", "end": "06:03", "title": "法治进行时"}, {"date": "2023-10-26", "start": "06:03", "end": "06:20", "title": "法治进行时"}, {"date": "2023-10-26", "start": "06:20", "end": "06:55", "title": "养生堂精编版"}, {"date": "2023-10-26", "start": "06:55", "end": "07:00", "title": "早间气象服务"}, {"date": "2023-10-26", "start": "07:00", "end": "09:07", "title": "北京您早"}, {"date": "2023-10-26", "start": "09:07", "end": "09:17", "title": "音乐大师课"}, {"date": "2023-10-26", "start": "09:17", "end": "10:18", "title": "特工任务(28)"}, {"date": "2023-10-26", "start": "10:18", "end": "11:09", "title": "特工任务(29)"}, {"date": "2023-10-26", "start": "11:09", "end": "12:00", "title": "特工任务(30)"}, {"date": "2023-10-26", "start": "12:00", "end": "12:58", "title": "特别关注"}, {"date": "2023-10-26", "start": "12:58", "end": "13:10", "title": "午间气象服务"}, {"date": "2023-10-26", "start": "13:10", "end": "14:02", "title": "大宅门(31)"}, {"date": "2023-10-26", "start": "14:02", "end": "14:55", "title": "大宅门(32)"}, {"date": "2023-10-26", "start": "14:55", "end": "15:48", "title": "大宅门(33)"}, {"date": "2023-10-26", "start": "15:48", "end": "16:40", "title": "大宅门(34)"}, {"date": "2023-10-26", "start": "16:40", "end": "17:25", "title": "暖暖的味道"}, {"date": "2023-10-26", "start": "17:25", "end": "18:30", "title": "养生堂"}, {"date": "2023-10-26", "start": "18:30", "end": "18:54", "title": "北京新闻"}, {"date": "2023-10-26", "start": "18:54", "end": "19:00", "title": "北京天气预报"}, {"date": "2023-10-26", "start": "19:00", "end": "19:32", "title": "转播央视新闻联播"}, {"date": "2023-10-26", "start": "19:32", "end": "20:19", "title": "梅花红桃(27)"}, {"date": "2023-10-26", "start": "20:19", "end": "21:05", "title": "梅花红桃(28)"}, {"date": "2023-10-26", "start": "21:05", "end": "21:43", "title": "我是大医生"}, {"date": "2023-10-26", "start": "21:43", "end": "22:31", "title": "老师请回答"}, {"date": "2023-10-26", "start": "22:31", "end": "23:11", "title": "我是大医生"}, {"date": "2023-10-26", "start": "23:11", "end": "23:52", "title": "父母爱情(6)"}, {"date": "2023-10-26", "start": "23:52", "end": "23:59", "title": "父母爱情(7)"}]}