{"channel_name": "第一剧场", "epg_data": [{"date": "2023-10-26", "start": "00:29", "end": "07:00", "title": "岁岁年年柿柿红-(高清文件)-2"}, {"date": "2023-10-26", "start": "07:00", "end": "07:46", "title": "岁岁年年柿柿红-(高清文件)-1"}, {"date": "2023-10-26", "start": "07:46", "end": "08:42", "title": "岁岁年年柿柿红-(高清文件)-2"}, {"date": "2023-10-26", "start": "08:42", "end": "09:28", "title": "巡回检察组-高清文件-18"}, {"date": "2023-10-26", "start": "09:28", "end": "10:14", "title": "巡回检察组-高清文件-19"}, {"date": "2023-10-26", "start": "10:14", "end": "11:00", "title": "巡回检察组-高清文件-20"}, {"date": "2023-10-26", "start": "11:00", "end": "12:00", "title": "巡回检察组-高清文件-21"}, {"date": "2023-10-26", "start": "12:00", "end": "12:46", "title": "明天我们好好过-高清文件-7"}, {"date": "2023-10-26", "start": "12:46", "end": "13:50", "title": "明天我们好好过-高清文件-8"}, {"date": "2023-10-26", "start": "13:50", "end": "14:36", "title": "黑白禁区-(高清文件)-16"}, {"date": "2023-10-26", "start": "14:36", "end": "15:22", "title": "黑白禁区-(高清文件)-17"}, {"date": "2023-10-26", "start": "15:22", "end": "16:08", "title": "黑白禁区-(高清文件)-18"}, {"date": "2023-10-26", "start": "16:08", "end": "16:54", "title": "黑白禁区-(高清文件)-19"}, {"date": "2023-10-26", "start": "16:54", "end": "17:40", "title": "黑白禁区-(高清文件)-20"}, {"date": "2023-10-26", "start": "17:40", "end": "18:41", "title": "黑白禁区-(高清文件)-21"}, {"date": "2023-10-26", "start": "18:41", "end": "19:27", "title": "巡回检察组-高清文件-22"}, {"date": "2023-10-26", "start": "19:27", "end": "20:13", "title": "巡回检察组-高清文件-23"}, {"date": "2023-10-26", "start": "20:13", "end": "20:59", "title": "巡回检察组-高清文件-24"}, {"date": "2023-10-26", "start": "20:59", "end": "22:00", "title": "巡回检察组-高清文件-25"}, {"date": "2023-10-26", "start": "22:00", "end": "22:46", "title": "明天我们好好过-高清文件-9"}, {"date": "2023-10-26", "start": "22:46", "end": "23:44", "title": "明天我们好好过-高清文件-10"}, {"date": "2023-10-26", "start": "23:44", "end": "23:59", "title": "岁岁年年柿柿红-(高清文件)-3"}]}